dubbo/__init__.py
dubbo/client.py
dubbo/codec/__init__.py
dubbo/codec/decoder.py
dubbo/codec/encoder.py
dubbo/common/__init__.py
dubbo/common/constants.py
dubbo/common/exceptions.py
dubbo/common/util.py
dubbo/connection/__init__.py
dubbo/connection/connections.py
python3_dubbo-0.0.8.dist-info/LICENSE
python3_dubbo-0.0.8.dist-info/METADATA
python3_dubbo-0.0.8.dist-info/WHEEL
python3_dubbo-0.0.8.dist-info/top_level.txt
python3_dubbo-0.0.8.dist-info/RECORD
