Metadata-Version: 2.2
Name: python3-dubbo
Version: 0.0.8
Summary: Python3 Dubbo Client.
Home-page: https://github.com/huisongyang/dubbo-python3
Author: yanghuisong
Author-email: yanghuisong@foxmail.com
License: Apache License 2.0
Classifier: Environment :: Console
Classifier: Intended Audience :: Developers
Classifier: Natural Language :: Chinese (Simplified)
Classifier: Operating System :: OS Independent
Classifier: Programming Language :: Python :: 3.9
Classifier: Programming Language :: Python :: 3 :: Only
License-File: LICENSE
Requires-Dist: kazoo==2.8.0
Dynamic: author
Dynamic: author-email
Dynamic: classifier
Dynamic: description
Dynamic: description-content-type
Dynamic: home-page
Dynamic: license
Dynamic: requires-dist
Dynamic: summary
